greenpulse_mcp/__init__.py
greenpulse_mcp/server.py
greenpulse_mcp-1.0.0.dist-info/WHEEL
greenpulse_mcp-1.0.0.dist-info/entry_points.txt
greenpulse_mcp-1.0.0.dist-info/METADATA
greenpulse_mcp-1.0.0.dist-info/RECORD
