Metadata-Version: 2.3
Name: greenpulse-mcp
Version: 1.0.0
Summary: greenpulse MCP server
Requires-Dist: mcp>=1.12.3
Requires-Dist: aiohttp
Requires-Python: >=3.11
